sunzhenyu59/i-verilog-assistant/demo_prj/src/add3.v
`timescale 1ns/1ps
/*
	@ File		: add3.v
	@ Author 	: Sun Zhenyu
	@ Data 		: 2022 - 02 - 10
	@ Version	:
	@ Brief		:
*/
module add3(
	input	[3:0]			in,
	output	[3:0]			out

);
	reg [3:0] 				out;
	always @(*) begin
			case(in)
				4'b0000: out = 4'b0000;  // 0
				4'b0001: out = 4'b0001;  // 1
				4'b0010: out = 4'b0010;  // 2
				4'b0011: out = 4'b0011;  // 3
				4'b0100: out = 4'b0100;  // 4
				4'b0101: out = 4'b1000;  // 5
				4'b0110: out = 4'b1001;  //6
				4'b0111: out = 4'b1010;  //7
				4'b1000: out = 4'b1011;  //8
				4'b1001: out = 4'b1100;  //9
				default: out = 4'b0000;  //others, impossible
			endcase
		end
endmodule

sunzhenyu59/i-verilog-assistant/demo_prj/src/bin2bcd.v
`timescale 1ns/1ps
/*
	@ File		: bin2bcd.v
	@ Author 	: User
	@ Data 		: 2022-02-10
	@ Version	:
	@ Brief		:
*/
module bin2bcd(
	input	[7:0]			bin,
	output	[11:0]			bcd

);
	wire 	[3:0] 			add3_inst0_out;
	wire 	[3:0] 			add3_inst1_out;
	wire 	[3:0] 			add3_inst2_out;
	wire 	[3:0] 			add3_inst3_out;
	wire 	[3:0] 			add3_inst4_out;
	wire 	[3:0] 			add3_inst5_out;
	wire 	[3:0] 			add3_inst6_out;
	
	assign bcd[11:8] = {2'b0,add3_inst5_out[3],add3_inst6_out[3]};
	assign bcd[7:4] = {add3_inst6_out[2:0],add3_inst4_out[3]};
	assign bcd[3:0] = {add3_inst4_out[2:0], bin[0]};
	add3 add3_inst0
	(
		.in({1'b0,bin[7:5]}),
		.out(add3_inst0_out)
	);
	add3 add3_inst1
	(
		.in({add3_inst0_out[2:0],bin[4]}),
		.out(add3_inst1_out)
	);
	add3 add3_inst2
	(
		.in({add3_inst1_out[2:0],bin[3]}),
		.out(add3_inst2_out)
	);
	add3 add3_inst3
	(
		.in({add3_inst2_out[2:0],bin[2]}),
		.out(add3_inst3_out)
	);
	add3 add3_inst4
	(
		.in({add3_inst3_out[2:0],bin[1]}),
		.out(add3_inst4_out)
	);
	add3 add3_inst5
	(
		.in({1'b0,add3_inst0_out[3],add3_inst1_out[3],add3_inst2_out[3]}),
		.out(add3_inst5_out)
	);
	add3 add3_inst6
	(
		.in({add3_inst5_out[2:0],add3_inst3_out[3]}),
		.out(add3_inst6_out)
	);
endmodule

sunzhenyu59/i-verilog-assistant/demo_prj/tb/test.v
`timescale 1ns/1ps
/*
	@ File		: test.v
	@ Author 	: User
	@ Data 		: 2022-02-10
	@ Version	:
	@ Brief		:
*/
module test_tb();
//************************Do Not Remove************************//
	initial begin
		$dumpfile("test_tb.vcd");
		$dumpvars();
	end
//*************************************************************//

reg[8:0] i;
reg [11:0] bcd;
wire [11:0] test_output;
reg [3:0] error_count;

bin2bcd bin2bcd_inst(
	.bin(i[7:0]),
	.bcd(test_output)
);

initial begin
	error_count = 0;
	for(i = 0;i <= 255; i = i + 1) begin
		bcd[3:0] = i % 10;
		bcd[7:4] = (i / 10) % 10;
		bcd[11:8] = (i / 100) % 10;
		#10;
		if(test_output != bcd) begin
			error_count = error_count + 1;
			$display("integer %d : hdl output [%d %d %d], correct [%d %d %d]\n", 
											i,
											test_output[11:8], test_output[7:4], test_output[3:0],
											bcd[11:8], bcd[7:4], bcd[3:0]
					);
		end		
	end
	if(error_count == 0)
		$display("Test pass!\n");
	else
		$display("%d error occurred while testing hdl module\b");
	$finish();
end

endmodule

sunzhenyu59/i-verilog-assistant/demo_prj/test_tb.vcd
$date
	Thu Feb 10 23:10:14 2022
$end
$version
	Icarus Verilog
$end
$timescale
	1ps
$end
$scope module test_tb $end
$var wire 12 ! test_output [11:0] $end
$var reg 12 " bcd [11:0] $end
$var reg 4 # error_count [3:0] $end
$var reg 9 $ i [8:0] $end
$scope module bin2bcd_inst $end
$var wire 8 % bin [7:0] $end
$var wire 12 & bcd [11:0] $end
$var wire 4 ' add3_inst6_out [3:0] $end
$var wire 4 ( add3_inst5_out [3:0] $end
$var wire 4 ) add3_inst4_out [3:0] $end
$var wire 4 * add3_inst3_out [3:0] $end
$var wire 4 + add3_inst2_out [3:0] $end
$var wire 4 , add3_inst1_out [3:0] $end
$var wire 4 - add3_inst0_out [3:0] $end
$scope module add3_inst0 $end
$var wire 4 . in [3:0] $end
$var reg 4 / out [3:0] $end
$upscope $end
$scope module add3_inst1 $end
$var wire 4 0 in [3:0] $end
$var reg 4 1 out [3:0] $end
$upscope $end
$scope module add3_inst2 $end
$var wire 4 2 in [3:0] $end
$var reg 4 3 out [3:0] $end
$upscope $end
$scope module add3_inst3 $end
$var wire 4 4 in [3:0] $end
$var reg 4 5 out [3:0] $end
$upscope $end
$scope module add3_inst4 $end
$var wire 4 6 in [3:0] $end
$var reg 4 7 out [3:0] $end
$upscope $end
$scope module add3_inst5 $end
$var wire 4 8 in [3:0] $end
$var reg 4 9 out [3:0] $end
$upscope $end
$scope module add3_inst6 $end
$var wire 4 : in [3:0] $end
$var reg 4 ; out [3:0] $end
$upscope $end
$upscope $end
$upscope $end
$enddefinitions $end
#0
$dumpvars
b0 ;
b0 :
b0 9
b0 8
b0 7
b0 6
b0 5
b0 4
b0 3
b0 2
b0 1
b0 0
b0 /
b0 .
b0 -
b0 ,
b0 +
b0 *
b0 )
b0 (
b0 '
b0 &
b0 %
b0 $
b0 #
b0 "
b0 !
$end
#10000
b1 !
b1 &
b1 %
b1 "
b1 $
#20000
b1 )
b1 7
b10 !
b10 &
b1 6
b10 %
b10 "
b10 $
#30000
b11 !
b11 &
b11 %
b11 "
b11 $
#40000
b1 *
b1 5
b10 )
b10 7
b100 !
b100 &
b1 4
b10 6
b100 %
b100 "
b100 $
#50000
b101 !
b101 &
b101 %
b101 "
b101 $
#60000
b11 )
b11 7
b110 !
b110 &
b11 6
b110 %
b110 "
b110 $
#70000
b111 !
b111 &
b111 %
b111 "
b111 $
#80000
b1 +
b1 3
b10 *
b10 5
b100 )
b100 7
b1000 !
b1000 &
b1 2
b10 4
b100 6
b1000 %
b1000 "
b1000 $
#90000
b1001 !
b1001 &
b1001 %
b1001 "
b1001 $
#100000
b1000 )
b1000 7
b10000 !
b10000 &
b101 6
b1010 %
b10000 "
b1010 $
#110000
b10001 !
b10001 &
b1011 %
b10001 "
b1011 $
#120000
b11 *
b11 5
b1001 )
b1001 7
b10010 !
b10010 &
b11 4
b110 6
b1100 %
b10010 "
b1100 $
#130000
b10011 !
b10011 &
b1101 %
b10011 "
b1101 $
#140000
b1010 )
b1010 7
b10100 !
b10100 &
b111 6
b1110 %
b10100 "
b1110 $
#150000
b10101 !
b10101 &
b1111 %
b10101 "
b1111 $
#160000
b1 ,
b1 1
b10 +
b10 3
b100 *
b100 5
b1011 )
b1011 7
b10110 !
b10110 &
b1 0
b10 2
b100 4
b1000 6
b10000 %
b10110 "
b10000 $
#170000
b10111 !
b10111 &
b10001 %
b10111 "
b10001 $
#180000
b1100 )
b1100 7
b11000 !
b11000 &
b1001 6
b10010 %
b11000 "
b10010 $
#190000
b11001 !
b11001 &
b10011 %
b11001 "
b10011 $
#200000
b1 '
b1 ;
b1 :
b1000 *
b1000 5
b0 )
b0 7
b100000 !
b100000 &
b101 4
b0 6
b10100 %
b100000 "
b10100 $
#210000
b100001 !
b100001 &
b10101 %
b100001 "
b10101 $
#220000
b1 )
b1 7
b100010 !
b100010 &
b1 6
b10110 %
b100010 "
b10110 $
#230000
b100011 !
b100011 &
b10111 %
b100011 "
b10111 $
#240000
b1 '
b1 ;
b1 :
b11 +
b11 3
b1001 *
b1001 5
b10 )
b10 7
b100100 !
b100100 &
b11 2
b110 4
b10 6
b11000 %
b100100 "
b11000 $
#250000
b100101 !
b100101 &
b11001 %
b100101 "
b11001 $
#260000
b11 )
b11 7
b100110 !
b100110 &
b11 6
b11010 %
b100110 "
b11010 $
#270000
b100111 !
b100111 &
b11011 %
b100111 "
b11011 $
#280000
b1010 *
b1010 5
b100 )
b100 7
b101000 !
b101000 &
b111 4
b100 6
b11100 %
b101000 "
b11100 $
#290000
b101001 !
b101001 &
b11101 %
b101001 "
b11101 $
#300000
b1000 )
b1000 7
b110000 !
b110000 &
b101 6
b11110 %
b110000 "
b11110 $
#310000
b110001 !
b110001 &
b11111 %
b110001 "
b11111 $
#320000
b1 '
b1 ;
b1 :
b1 -
b1 /
b10 ,
b10 1
b100 +
b100 3
b1011 *
b1011 5
b1001 )
b1001 7
b110010 !
b110010 &
b1 .
b10 0
b100 2
b1000 4
b110 6
b100000 %
b110010 "
b100000 $
#330000
b110011 !
b110011 &
b100001 %
b110011 "
b100001 $
#340000
b1010 )
b1010 7
b110100 !
b110100 &
b111 6
b100010 %
b110100 "
b100010 $
#350000
b110101 !
b110101 &
b100011 %
b110101 "
b100011 $
#360000
b1100 *
b1100 5
b1011 )
b1011 7
b110110 !
b110110 &
b1001 4
b1000 6
b100100 %
b110110 "
b100100 $
#370000
b110111 !
b110111 &
b100101 %
b110111 "
b100101 $
#380000
b1100 )
b1100 7
b111000 !
b111000 &
b1001 6
b100110 %
b111000 "
b100110 $
#390000
b111001 !
b111001 &
b100111 %
b111001 "
b100111 $
#400000
b10 '
b10 ;
b10 :
b1 (
b1 9
b1 8
b1000 +
b1000 3
b0 *
b0 5
b0 )
b0 7
b1000000 !
b1000000 &
b101 2
b0 4
b0 6
b101000 %
b1000000 "
b101000 $
#410000
b1000001 !
b1000001 &
b101001 %
b1000001 "
b101001 $
#420000
b1 )
b1 7
b1000010 !
b1000010 &
b1 6
b101010 %
b1000010 "
b101010 $
#430000
b1000011 !
b1000011 &
b101011 %
b1000011 "
b101011 $
#440000
b1 *
b1 5
b10 )
b10 7
b1000100 !
b1000100 &
b1 4
b10 6
b101100 %
b1000100 "
b101100 $
#450000
b1000101 !
b1000101 &
b101101 %
b1000101 "
b101101 $
#460000
b11 )
b11 7
b1000110 !
b1000110 &
b11 6
b101110 %
b1000110 "
b101110 $
#470000
b1000111 !
b1000111 &
b101111 %
b1000111 "
b101111 $
#480000
b10 '
b10 ;
b10 :
b1 (
b1 9
b1 8
b11 ,
b11 1
b1001 +
b1001 3
b10 *
b10 5
b100 )
b100 7
b1001000 !
b1001000 &
b11 0
b110 2
b10 4
b100 6
b110000 %
b1001000 "
b110000 $
#490000
b1001001 !
b1001001 &
b110001 %
b1001001 "
b110001 $
#500000
b1000 )
b1000 7
b1010000 !
b1010000 &
b101 6
b110010 %
b1010000 "
b110010 $
#510000
b1010001 !
b1010001 &
b110011 %
b1010001 "
b110011 $
#520000
b11 *
b11 5
b1001 )
b1001 7
b1010010 !
b1010010 &
b11 4
b110 6
b110100 %
b1010010 "
b110100 $
#530000
b1010011 !
b1010011 &
b110101 %
b1010011 "
b110101 $
#540000
b1010 )
b1010 7
b1010100 !
b1010100 &
b111 6
b110110 %
b1010100 "
b110110 $
#550000
b1010101 !
b1010101 &
b110111 %
b1010101 "
b110111 $
#560000
b1010 +
b1010 3
b100 *
b100 5
b1011 )
b1011 7
b1010110 !
b1010110 &
b111 2
b100 4
b1000 6
b111000 %
b1010110 "
b111000 $
#570000
b1010111 !
b1010111 &
b111001 %
b1010111 "
b111001 $
#580000
b1100 )
b1100 7
b1011000 !
b1011000 &
b1001 6
b111010 %
b1011000 "
b111010 $
#590000
b1011001 !
b1011001 &
b111011 %
b1011001 "
b111011 $
#600000
b11 '
b11 ;
b11 :
b1000 *
b1000 5
b0 )
b0 7
b1100000 !
b1100000 &
b101 4
b0 6
b111100 %
b1100000 "
b111100 $
#610000
b1100001 !
b1100001 &
b111101 %
b1100001 "
b111101 $
#620000
b1 )
b1 7
b1100010 !
b1100010 &
b1 6
b111110 %
b1100010 "
b111110 $
#630000
b1100011 !
b1100011 &
b111111 %
b1100011 "
b111111 $
#640000
b1 (
b1 9
b1 8
b11 '
b11 ;
b11 :
b10 -
b10 /
b100 ,
b100 1
b1011 +
b1011 3
b1001 *
b1001 5
b10 )
b10 7
b1100100 !
b1100100 &
b10 .
b100 0
b1000 2
b110 4
b10 6
b1000000 %
b1100100 "
b1000000 $
#650000
b1100101 !
b1100101 &
b1000001 %
b1100101 "
b1000001 $
#660000
b11 )
b11 7
b1100110 !
b1100110 &
b11 6
b1000010 %
b1100110 "
b1000010 $
#670000
b1100111 !
b1100111 &
b1000011 %
b1100111 "
b1000011 $
#680000
b1010 *
b1010 5
b100 )
b100 7
b1101000 !
b1101000 &
b111 4
b100 6
b1000100 %
b1101000 "
b1000100 $
#690000
b1101001 !
b1101001 &
b1000101 %
b1101001 "
b1000101 $
#700000
b1000 )
b1000 7
b1110000 !
b1110000 &
b101 6
b1000110 %
b1110000 "
b1000110 $
#710000
b1110001 !
b1110001 &
b1000111 %
b1110001 "
b1000111 $
#720000
b1100 +
b1100 3
b1011 *
b1011 5
b1001 )
b1001 7
b1110010 !
b1110010 &
b1001 2
b1000 4
b110 6
b1001000 %
b1110010 "
b1001000 $
#730000
b1110011 !
b1110011 &
b1001001 %
b1110011 "
b1001001 $
#740000
b1010 )
b1010 7
b1110100 !
b1110100 &
b111 6
b1001010 %
b1110100 "
b1001010 $
#750000
b1110101 !
b1110101 &
b1001011 %
b1110101 "
b1001011 $
#760000
b1100 *
b1100 5
b1011 )
b1011 7
b1110110 !
b1110110 &
b1001 4
b1000 6
b1001100 %
b1110110 "
b1001100 $
#770000
b1110111 !
b1110111 &
b1001101 %
b1110111 "
b1001101 $
#780000
b1100 )
b1100 7
b1111000 !
b1111000 &
b1001 6
b1001110 %
b1111000 "
b1001110 $
#790000
b1111001 !
b1111001 &
b1001111 %
b1111001 "
b1001111 $
#800000
b100 '
b100 ;
b100 :
b10 (
b10 9
b10 8
b1000 ,
b1000 1
b0 +
b0 3
b0 *
b0 5
b0 )
b0 7
b10000000 !
b10000000 &
b101 0
b0 2
b0 4
b0 6
b1010000 %
b10000000 "
b1010000 $
#810000
b10000001 !
b10000001 &
b1010001 %
b10000001 "
b1010001 $
#820000
b1 )
b1 7
b10000010 !
b10000010 &
b1 6
b1010010 %
b10000010 "
b1010010 $
#830000
b10000011 !
b10000011 &
b1010011 %
b10000011 "
b1010011 $
#840000
b1 *
b1 5
b10 )
b10 7
b10000100 !
b10000100 &
b1 4
b10 6
b1010100 %
b10000100 "
b1010100 $
#850000
b10000101 !
b10000101 &
b1010101 %
b10000101 "
b1010101 $
#860000
b11 )
b11 7
b10000110 !
b10000110 &
b11 6
b1010110 %
b10000110 "
b1010110 $
#870000
b10000111 !
b10000111 &
b1010111 %
b10000111 "
b1010111 $
#880000
b1 +
b1 3
b10 *
b10 5
b100 )
b100 7
b10001000 !
b10001000 &
b1 2
b10 4
b100 6
b1011000 %
b10001000 "
b1011000 $
#890000
b10001001 !
b10001001 &
b1011001 %
b10001001 "
b1011001 $
#900000
b1000 )
b1000 7
b10010000 !
b10010000 &
b101 6
b1011010 %
b10010000 "
b1011010 $
#910000
b10010001 !
b10010001 &
b1011011 %
b10010001 "
b1011011 $
#920000
b11 *
b11 5
b1001 )
b1001 7
b10010010 !
b10010010 &
b11 4
b110 6
b1011100 %
b10010010 "
b1011100 $
#930000
b10010011 !
b10010011 &
b1011101 %
b10010011 "
b1011101 $
#940000
b1010 )
b1010 7
b10010100 !
b10010100 &
b111 6
b1011110 %
b10010100 "
b1011110 $
#950000
b10010101 !
b10010101 &
b1011111 %
b10010101 "
b1011111 $
#960000
b100 '
b100 ;
b100 :
b10 (
b10 9
b10 8
b11 -
b11 /
b1001 ,
b1001 1
b10 +
b10 3
b100 *
b100 5
b1011 )
b1011 7
b10010110 !
b10010110 &
b11 .
b110 0
b10 2
b100 4
b1000 6
b1100000 %
b10010110 "
b1100000 $
#970000
b10010111 !
b10010111 &
b1100001 %
b10010111 "
b1100001 $
#980000
b1100 )
b1100 7
b10011000 !
b10011000 &
b1001 6
b1100010 %
b10011000 "
b1100010 $
#990000
b10011001 !
b10011001 &
b1100011 %
b10011001 "
b1100011 $
#1000000
b1000 '
b1000 ;
b101 :
b1000 *
b1000 5
b0 )
b0 7
b100000000 !
b100000000 &
b101 4
b0 6
b1100100 %
b100000000 "
b1100100 $
#1010000
b100000001 !
b100000001 &
b1100101 %
b100000001 "
b1100101 $
#1020000
b1 )
b1 7
b100000010 !
b100000010 &
b1 6
b1100110 %
b100000010 "
b1100110 $
#1030000
b100000011 !
b100000011 &
b1100111 %
b100000011 "
b1100111 $
#1040000
b1000 '
b1000 ;
b101 :
b11 +
b11 3
b1001 *
b1001 5
b10 )
b10 7
b100000100 !
b100000100 &
b11 2
b110 4
b10 6
b1101000 %
b100000100 "
b1101000 $
#1050000
b100000101 !
b100000101 &
b1101001 %
b100000101 "
b1101001 $
#1060000
b11 )
b11 7
b100000110 !
b100000110 &
b11 6
b1101010 %
b100000110 "
b1101010 $
#1070000
b100000111 !
b100000111 &
b1101011 %
b100000111 "
b1101011 $
#1080000
b1010 *
b1010 5
b100 )
b100 7
b100001000 !
b100001000 &
b111 4
b100 6
b1101100 %
b100001000 "
b1101100 $
#1090000
b100001001 !
b100001001 &
b1101101 %
b100001001 "
b1101101 $
#1100000
b1000 )
b1000 7
b100010000 !
b100010000 &
b101 6
b1101110 %
b100010000 "
b1101110 $
#1110000
b100010001 !
b100010001 &
b1101111 %
b100010001 "
b1101111 $
#1120000
b1000 '
b1000 ;
b101 :
b1010 ,
b1010 1
b100 +
b100 3
b1011 *
b1011 5
b1001 )
b1001 7
b100010010 !
b100010010 &
b111 0
b100 2
b1000 4
b110 6
b1110000 %
b100010010 "
b1110000 $
#1130000
b100010011 !
b100010011 &
b1110001 %
b100010011 "
b1110001 $
#1140000
b1010 )
b1010 7
b100010100 !
b100010100 &
b111 6
b1110010 %
b100010100 "
b1110010 $
#1150000
b100010101 !
b100010101 &
b1110011 %
b100010101 "
b1110011 $
#1160000
b1100 *
b1100 5
b1011 )
b1011 7
b100010110 !
b100010110 &
b1001 4
b1000 6
b1110100 %
b100010110 "
b1110100 $
#1170000
b100010111 !
b100010111 &
b1110101 %
b100010111 "
b1110101 $
#1180000
b1100 )
b1100 7
b100011000 !
b100011000 &
b1001 6
b1110110 %
b100011000 "
b1110110 $
#1190000
b100011001 !
b100011001 &
b1110111 %
b100011001 "
b1110111 $
#1200000
b1001 '
b1001 ;
b110 :
b11 (
b11 9
b11 8
b1000 +
b1000 3
b0 *
b0 5
b0 )
b0 7
b100100000 !
b100100000 &
b101 2
b0 4
b0 6
b1111000 %
b100100000 "
b1111000 $
#1210000
b100100001 !
b100100001 &
b1111001 %
b100100001 "
b1111001 $
#1220000
b1 )
b1 7
b100100010 !
b100100010 &
b1 6
b1111010 %
b100100010 "
b1111010 $
#1230000
b100100011 !
b100100011 &
b1111011 %
b100100011 "
b1111011 $
#1240000
b1 *
b1 5
b10 )
b10 7
b100100100 !
b100100100 &
b1 4
b10 6
b1111100 %
b100100100 "
b1111100 $
#1250000
b100100101 !
b100100101 &
b1111101 %
b100100101 "
b1111101 $
#1260000
b11 )
b11 7
b100100110 !
b100100110 &
b11 6
b1111110 %
b100100110 "
b1111110 $
#1270000
b100100111 !
b100100111 &
b1111111 %
b100100111 "
b1111111 $
#1280000
b1001 '
b1001 ;
b110 :
b11 (
b11 9
b11 8
b100 -
b100 /
b1011 ,
b1011 1
b1001 +
b1001 3
b10 *
b10 5
b100 )
b100 7
b100101000 !
b100101000 &
b100 .
b1000 0
b110 2
b10 4
b100 6
b10000000 %
b100101000 "
b10000000 $
#1290000
b100101001 !
b100101001 &
b10000001 %
b100101001 "
b10000001 $
#1300000
b1000 )
b1000 7
b100110000 !
b100110000 &
b101 6
b10000010 %
b100110000 "
b10000010 $
#1310000
b100110001 !
b100110001 &
b10000011 %
b100110001 "
b10000011 $
#1320000
b11 *
b11 5
b1001 )
b1001 7
b100110010 !
b100110010 &
b11 4
b110 6
b10000100 %
b100110010 "
b10000100 $
#1330000
b100110011 !
b100110011 &
b10000101 %
b100110011 "
b10000101 $
#1340000
b1010 )
b1010 7
b100110100 !
b100110100 &
b111 6
b10000110 %
b100110100 "
b10000110 $
#1350000
b100110101 !
b100110101 &
b10000111 %
b100110101 "
b10000111 $
#1360000
b1010 +
b1010 3
b100 *
b100 5
b1011 )
b1011 7
b100110110 !
b100110110 &
b111 2
b100 4
b1000 6
b10001000 %
b100110110 "
b10001000 $
#1370000
b100110111 !
b100110111 &
b10001001 %
b100110111 "
b10001001 $
#1380000
b1100 )
b1100 7
b100111000 !
b100111000 &
b1001 6
b10001010 %
b100111000 "
b10001010 $
#1390000
b100111001 !
b100111001 &
b10001011 %
b100111001 "
b10001011 $
#1400000
b1010 '
b1010 ;
b111 :
b1000 *
b1000 5
b0 )
b0 7
b101000000 !
b101000000 &
b101 4
b0 6
b10001100 %
b101000000 "
b10001100 $
#1410000
b101000001 !
b101000001 &
b10001101 %
b101000001 "
b10001101 $
#1420000
b1 )
b1 7
b101000010 !
b101000010 &
b1 6
b10001110 %
b101000010 "
b10001110 $
#1430000
b101000011 !
b101000011 &
b10001111 %
b101000011 "
b10001111 $
#1440000
b1010 '
b1010 ;
b111 :
b1100 ,
b1100 1
b1011 +
b1011 3
b1001 *
b1001 5
b10 )
b10 7
b101000100 !
b101000100 &
b1001 0
b1000 2
b110 4
b10 6
b10010000 %
b101000100 "
b10010000 $
#1450000
b101000101 !
b101000101 &
b10010001 %
b101000101 "
b10010001 $
#1460000
b11 )
b11 7
b101000110 !
b101000110 &
b11 6
b10010010 %
b101000110 "
b10010010 $
#1470000
b101000111 !
b101000111 &
b10010011 %
b101000111 "
b10010011 $
#1480000
b1010 *
b1010 5
b100 )
b100 7
b101001000 !
b101001000 &
b111 4
b100 6
b10010100 %
b101001000 "
b10010100 $
#1490000
b101001001 !
b101001001 &
b10010101 %
b101001001 "
b10010101 $
#1500000
b1000 )
b1000 7
b101010000 !
b101010000 &
b101 6
b10010110 %
b101010000 "
b10010110 $
#1510000
b101010001 !
b101010001 &
b10010111 %
b101010001 "
b10010111 $
#1520000
b1100 +
b1100 3
b1011 *
b1011 5
b1001 )
b1001 7
b101010010 !
b101010010 &
b1001 2
b1000 4
b110 6
b10011000 %
b101010010 "
b10011000 $
#1530000
b101010011 !
b101010011 &
b10011001 %
b101010011 "
b10011001 $
#1540000
b1010 )
b1010 7
b101010100 !
b101010100 &
b111 6
b10011010 %
b101010100 "
b10011010 $
#1550000
b101010101 !
b101010101 &
b10011011 %
b101010101 "
b10011011 $
#1560000
b1100 *
b1100 5
b1011 )
b1011 7
b101010110 !
b101010110 &
b1001 4
b1000 6
b10011100 %
b101010110 "
b10011100 $
#1570000
b101010111 !
b101010111 &
b10011101 %
b101010111 "
b10011101 $
#1580000
b1100 )
b1100 7
b101011000 !
b101011000 &
b1001 6
b10011110 %
b101011000 "
b10011110 $
#1590000
b101011001 !
b101011001 &
b10011111 %
b101011001 "
b10011111 $
#1600000
b1011 '
b1011 ;
b1000 :
b100 (
b100 9
b100 8
b1000 -
b1000 /
b0 ,
b0 1
b0 +
b0 3
b0 *
b0 5
b0 )
b0 7
b101100000 !
b101100000 &
b101 .
b0 0
b0 2
b0 4
b0 6
b10100000 %
b101100000 "
b10100000 $
#1610000
b101100001 !
b101100001 &
b10100001 %
b101100001 "
b10100001 $
#1620000
b1 )
b1 7
b101100010 !
b101100010 &
b1 6
b10100010 %
b101100010 "
b10100010 $
#1630000
b101100011 !
b101100011 &
b10100011 %
b101100011 "
b10100011 $
#1640000
b1 *
b1 5
b10 )
b10 7
b101100100 !
b101100100 &
b1 4
b10 6
b10100100 %
b101100100 "
b10100100 $
#1650000
b101100101 !
b101100101 &
b10100101 %
b101100101 "
b10100101 $
#1660000
b11 )
b11 7
b101100110 !
b101100110 &
b11 6
b10100110 %
b101100110 "
b10100110 $
#1670000
b101100111 !
b101100111 &
b10100111 %
b101100111 "
b10100111 $
#1680000
b1 +
b1 3
b10 *
b10 5
b100 )
b100 7
b101101000 !
b101101000 &
b1 2
b10 4
b100 6
b10101000 %
b101101000 "
b10101000 $
#1690000
b101101001 !
b101101001 &
b10101001 %
b101101001 "
b10101001 $
#1700000
b1000 )
b1000 7
b101110000 !
b101110000 &
b101 6
b10101010 %
b101110000 "
b10101010 $
#1710000
b101110001 !
b101110001 &
b10101011 %
b101110001 "
b10101011 $
#1720000
b11 *
b11 5
b1001 )
b1001 7
b101110010 !
b101110010 &
b11 4
b110 6
b10101100 %
b101110010 "
b10101100 $
#1730000
b101110011 !
b101110011 &
b10101101 %
b101110011 "
b10101101 $
#1740000
b1010 )
b1010 7
b101110100 !
b101110100 &
b111 6
b10101110 %
b101110100 "
b10101110 $
#1750000
b101110101 !
b101110101 &
b10101111 %
b101110101 "
b10101111 $
#1760000
b1 ,
b1 1
b10 +
b10 3
b100 *
b100 5
b1011 )
b1011 7
b101110110 !
b101110110 &
b1 0
b10 2
b100 4
b1000 6
b10110000 %
b101110110 "
b10110000 $
#1770000
b101110111 !
b101110111 &
b10110001 %
b101110111 "
b10110001 $
#1780000
b1100 )
b1100 7
b101111000 !
b101111000 &
b1001 6
b10110010 %
b101111000 "
b10110010 $
#1790000
b101111001 !
b101111001 &
b10110011 %
b101111001 "
b10110011 $
#1800000
b1100 '
b1100 ;
b1001 :
b1000 *
b1000 5
b0 )
b0 7
b110000000 !
b110000000 &
b101 4
b0 6
b10110100 %
b110000000 "
b10110100 $
#1810000
b110000001 !
b110000001 &
b10110101 %
b110000001 "
b10110101 $
#1820000
b1 )
b1 7
b110000010 !
b110000010 &
b1 6
b10110110 %
b110000010 "
b10110110 $
#1830000
b110000011 !
b110000011 &
b10110111 %
b110000011 "
b10110111 $
#1840000
b1100 '
b1100 ;
b1001 :
b11 +
b11 3
b1001 *
b1001 5
b10 )
b10 7
b110000100 !
b110000100 &
b11 2
b110 4
b10 6
b10111000 %
b110000100 "
b10111000 $
#1850000
b110000101 !
b110000101 &
b10111001 %
b110000101 "
b10111001 $
#1860000
b11 )
b11 7
b110000110 !
b110000110 &
b11 6
b10111010 %
b110000110 "
b10111010 $
#1870000
b110000111 !
b110000111 &
b10111011 %
b110000111 "
b10111011 $
#1880000
b1010 *
b1010 5
b100 )
b100 7
b110001000 !
b110001000 &
b111 4
b100 6
b10111100 %
b110001000 "
b10111100 $
#1890000
b110001001 !
b110001001 &
b10111101 %
b110001001 "
b10111101 $
#1900000
b1000 )
b1000 7
b110010000 !
b110010000 &
b101 6
b10111110 %
b110010000 "
b10111110 $
#1910000
b110010001 !
b110010001 &
b10111111 %
b110010001 "
b10111111 $
#1920000
b1100 '
b1100 ;
b1001 :
b1001 -
b1001 /
b10 ,
b10 1
b100 +
b100 3
b1011 *
b1011 5
b1001 )
b1001 7
b110010010 !
b110010010 &
b110 .
b10 0
b100 2
b1000 4
b110 6
b11000000 %
b110010010 "
b11000000 $
#1930000
b110010011 !
b110010011 &
b11000001 %
b110010011 "
b11000001 $
#1940000
b1010 )
b1010 7
b110010100 !
b110010100 &
b111 6
b11000010 %
b110010100 "
b11000010 $
#1950000
b110010101 !
b110010101 &
b11000011 %
b110010101 "
b11000011 $
#1960000
b1100 *
b1100 5
b1011 )
b1011 7
b110010110 !
b110010110 &
b1001 4
b1000 6
b11000100 %
b110010110 "
b11000100 $
#1970000
b110010111 !
b110010111 &
b11000101 %
b110010111 "
b11000101 $
#1980000
b1100 )
b1100 7
b110011000 !
b110011000 &
b1001 6
b11000110 %
b110011000 "
b11000110 $
#1990000
b110011001 !
b110011001 &
b11000111 %
b110011001 "
b11000111 $
#2000000
b0 '
b0 ;
b0 :
b1000 (
b1000 9
b101 8
b1000 +
b1000 3
b0 *
b0 5
b0 )
b0 7
b1000000000 !
b1000000000 &
b101 2
b0 4
b0 6
b11001000 %
b1000000000 "
b11001000 $
#2010000
b1000000001 !
b1000000001 &
b11001001 %
b1000000001 "
b11001001 $
#2020000
b1 )
b1 7
b1000000010 !
b1000000010 &
b1 6
b11001010 %
b1000000010 "
b11001010 $
#2030000
b1000000011 !
b1000000011 &
b11001011 %
b1000000011 "
b11001011 $
#2040000
b1 *
b1 5
b10 )
b10 7
b1000000100 !
b1000000100 &
b1 4
b10 6
b11001100 %
b1000000100 "
b11001100 $
#2050000
b1000000101 !
b1000000101 &
b11001101 %
b1000000101 "
b11001101 $
#2060000
b11 )
b11 7
b1000000110 !
b1000000110 &
b11 6
b11001110 %
b1000000110 "
b11001110 $
#2070000
b1000000111 !
b1000000111 &
b11001111 %
b1000000111 "
b11001111 $
#2080000
b0 '
b0 ;
b0 :
b1000 (
b1000 9
b101 8
b11 ,
b11 1
b1001 +
b1001 3
b10 *
b10 5
b100 )
b100 7
b1000001000 !
b1000001000 &
b11 0
b110 2
b10 4
b100 6
b11010000 %
b1000001000 "
b11010000 $
#2090000
b1000001001 !
b1000001001 &
b11010001 %
b1000001001 "
b11010001 $
#2100000
b1000 )
b1000 7
b1000010000 !
b1000010000 &
b101 6
b11010010 %
b1000010000 "
b11010010 $
#2110000
b1000010001 !
b1000010001 &
b11010011 %
b1000010001 "
b11010011 $
#2120000
b11 *
b11 5
b1001 )
b1001 7
b1000010010 !
b1000010010 &
b11 4
b110 6
b11010100 %
b1000010010 "
b11010100 $
#2130000
b1000010011 !
b1000010011 &
b11010101 %
b1000010011 "
b11010101 $
#2140000
b1010 )
b1010 7
b1000010100 !
b1000010100 &
b111 6
b11010110 %
b1000010100 "
b11010110 $
#2150000
b1000010101 !
b1000010101 &
b11010111 %
b1000010101 "
b11010111 $
#2160000
b1010 +
b1010 3
b100 *
b100 5
b1011 )
b1011 7
b1000010110 !
b1000010110 &
b111 2
b100 4
b1000 6
b11011000 %
b1000010110 "
b11011000 $
